Tensorflow2HeKerasGaojiShenduXuexiChuyiFix1/README.md
Tensorflow2HeKerasGaojiShenduXuexiChuyiFix1/__init__.py
Tensorflow2HeKerasGaojiShenduXuexiChuyiFix1/__main__.py
Tensorflow2HeKerasGaojiShenduXuexiChuyiFix1/file.epub
Tensorflow2HeKerasGaojiShenduXuexiChuyiFix1/index.html
Tensorflow2HeKerasGaojiShenduXuexiChuyiFix1/css/__init__.py
Tensorflow2HeKerasGaojiShenduXuexiChuyiFix1/css/annotations.css
Tensorflow2HeKerasGaojiShenduXuexiChuyiFix1/css/main.css
Tensorflow2HeKerasGaojiShenduXuexiChuyiFix1/css/normalize.css
Tensorflow2HeKerasGaojiShenduXuexiChuyiFix1/css/popup.css
Tensorflow2HeKerasGaojiShenduXuexiChuyiFix1/font/__init__.py
Tensorflow2HeKerasGaojiShenduXuexiChuyiFix1/font/fontello.eot
Tensorflow2HeKerasGaojiShenduXuexiChuyiFix1/font/fontello.svg
Tensorflow2HeKerasGaojiShenduXuexiChuyiFix1/font/fontello.ttf
Tensorflow2HeKerasGaojiShenduXuexiChuyiFix1/font/fontello.woff
Tensorflow2HeKerasGaojiShenduXuexiChuyiFix1/img/__init__.py
Tensorflow2HeKerasGaojiShenduXuexiChuyiFix1/img/annotator-glyph-sprite.png
Tensorflow2HeKerasGaojiShenduXuexiChuyiFix1/img/annotator-icon-sprite.png
Tensorflow2HeKerasGaojiShenduXuexiChuyiFix1/img/apple-touch-icon.png
Tensorflow2HeKerasGaojiShenduXuexiChuyiFix1/img/cancelfullscreen.png
Tensorflow2HeKerasGaojiShenduXuexiChuyiFix1/img/close.png
Tensorflow2HeKerasGaojiShenduXuexiChuyiFix1/img/fullscreen.png
Tensorflow2HeKerasGaojiShenduXuexiChuyiFix1/img/loader.gif
Tensorflow2HeKerasGaojiShenduXuexiChuyiFix1/img/menu-icon.png
Tensorflow2HeKerasGaojiShenduXuexiChuyiFix1/img/save.png
Tensorflow2HeKerasGaojiShenduXuexiChuyiFix1/img/saved.png
Tensorflow2HeKerasGaojiShenduXuexiChuyiFix1/img/settings-s.png
Tensorflow2HeKerasGaojiShenduXuexiChuyiFix1/img/settings.png
Tensorflow2HeKerasGaojiShenduXuexiChuyiFix1/img/star.png
Tensorflow2HeKerasGaojiShenduXuexiChuyiFix1/js/__init__.py
Tensorflow2HeKerasGaojiShenduXuexiChuyiFix1/js/epub.js
Tensorflow2HeKerasGaojiShenduXuexiChuyiFix1/js/epub.min.js
tensorflow_2_he_keras_gaoji_shendu_xuexi_chuyi_fix1-2025.3.25.0.dist-info/METADATA
tensorflow_2_he_keras_gaoji_shendu_xuexi_chuyi_fix1-2025.3.25.0.dist-info/WHEEL
tensorflow_2_he_keras_gaoji_shendu_xuexi_chuyi_fix1-2025.3.25.0.dist-info/entry_points.txt
tensorflow_2_he_keras_gaoji_shendu_xuexi_chuyi_fix1-2025.3.25.0.dist-info/top_level.txt
tensorflow_2_he_keras_gaoji_shendu_xuexi_chuyi_fix1-2025.3.25.0.dist-info/RECORD
